{
    "list": [
        {
            "_inputName": "HandTracking",
            "_interactionName": "VirtualButtons",
            "_seconds": 21.221101760864259,
            "_countGrabInteraction": 0,
            "_countReleaseInteraction": 0,
            "_countTouchInteraction": 9
        },
        {
            "_inputName": "HandTracking",
            "_interactionName": "Dice",
            "_seconds": 66.9371337890625,
            "_countGrabInteraction": 5,
            "_countReleaseInteraction": 4,
            "_countTouchInteraction": 0
        },
        {
            "_inputName": "HandTracking",
            "_interactionName": "GrabAndPlace",
            "_seconds": 16.411691665649415,
            "_countGrabInteraction": 7,
            "_countReleaseInteraction": 8,
            "_countTouchInteraction": 0
        },
        {
            "_inputName": "HandTracking",
            "_interactionName": "LightSwitch",
            "_seconds": 23.673742294311525,
            "_countGrabInteraction": 0,
            "_countReleaseInteraction": 0,
            "_countTouchInteraction": 10
        },
        {
            "_inputName": "HandTracking",
            "_interactionName": "Hanoi",
            "_seconds": 13.159111022949219,
            "_countGrabInteraction": 6,
            "_countReleaseInteraction": 6,
            "_countTouchInteraction": 3
        },
        {
            "_inputName": "HandTracking",
            "_interactionName": "ThrowObject",
            "_seconds": 38.567134857177737,
            "_countGrabInteraction": 0,
            "_countReleaseInteraction": 0,
            "_countTouchInteraction": 0
        }
    ]
}